arrangepy/__init__.py
arrangepy/__main__.py
arrangepy/cli.py
arrangepy/func.py
arrangepy/main.py
arrangepy/utils.py
arrangepy/web.py
arrangepy/static/ArrangePy.jpg
arrangepy/static/CleanPy.jpg
arrangepy/static/pagestyle.css
arrangepy/templates/base.html
arrangepy/templates/change.html
arrangepy/templates/completed.html
arrangepy/templates/error404.html
arrangepy/templates/index.html
lib/__init__.py
lib/arrange.py
lib/utils.py
webapp/__init__.py
webapp/web.py
webapp/static/ArrangePy.jpg
webapp/static/CleanPy.jpg
webapp/static/pagestyle.css
webapp/templates/base.html
webapp/templates/change.html
webapp/templates/completed.html
webapp/templates/error404.html
webapp/templates/index.html
arrangepy-1.1.2.dist-info/METADATA
arrangepy-1.1.2.dist-info/WHEEL
arrangepy-1.1.2.dist-info/entry_points.txt
arrangepy-1.1.2.dist-info/top_level.txt
arrangepy-1.1.2.dist-info/RECORD
