Metadata-Version: 2.1
Name: arrangepy
Version: 1.1.2
Summary: Arrange your files in distinct folder, help you clean your PC
Home-page: https://github.com/prashantsengar/ArrangePy
Author: Prashant Sengar
License: MIT
Keywords: arrange files windows cleaning tool open source prashant sengar
Platform: UNKNOWN
Requires-Dist: flask
